py_github_analyzer/__init__.py
py_github_analyzer/async_github_client.py
py_github_analyzer/cli.py
py_github_analyzer/config.py
py_github_analyzer/core.py
py_github_analyzer/exceptions.py
py_github_analyzer/file_processor.py
py_github_analyzer/github_client.py
py_github_analyzer/logger.py
py_github_analyzer/metadata_generator.py
py_github_analyzer/py.typed
py_github_analyzer/utils.py
py_github_analyzer-1.0.0.dist-info/licenses/LICENSE
py_github_analyzer-1.0.0.dist-info/METADATA
py_github_analyzer-1.0.0.dist-info/WHEEL
py_github_analyzer-1.0.0.dist-info/entry_points.txt
py_github_analyzer-1.0.0.dist-info/top_level.txt
py_github_analyzer-1.0.0.dist-info/RECORD
