Metadata-Version: 2.4
Name: py-github-analyzer
Version: 1.0.0
Summary: Advanced GitHub repository analyzer with AI-optimized code extraction and metadata generation
Author-email: Han Jun-hee <createbrain2heart@gmail.com>
Maintainer-email: Han Jun-hee <createbrain2heart@gmail.com>
License: MIT License
Project-URL: Homepage, https://github.com/creatorjun/github-analyzer
Project-URL: Documentation, https://github.com/creatorjun/github-analyzer#readme
Project-URL: Repository, https://github.com/creatorjun/github-analyzer.git
Project-URL: Bug Tracker, https://github.com/creatorjun/github-analyzer/issues
Project-URL: Feature Requests, https://github.com/creatorjun/github-analyzer/discussions
Project-URL: Changelog, https://github.com/creatorjun/github-analyzer/blob/main/CHANGELOG.md
Project-URL: Source Code, https://github.com/creatorjun/github-analyzer
Project-URL: Download, https://pypi.org/project/py-github-analyzer/
Keywords: github,analyzer,repository,code,extraction,metadata,ai,development,automation,git
Classifier: Development Status :: 5 - Production/Stable
Classifier: Intended Audience :: Developers
Classifier: Intended Audience :: Information Technology
Classifier: Intended Audience :: System Administrators
Classifier: License :: OSI Approved :: MIT License
Classifier: Operating System :: OS Independent
Classifier: Operating System :: MacOS
Classifier: Operating System :: Microsoft :: Windows
Classifier: Operating System :: POSIX :: Linux
Classifier: Programming Language :: Python :: 3
Classifier: Programming Language :: Python :: 3.8
Classifier: Programming Language :: Python :: 3.9
Classifier: Programming Language :: Python :: 3.10
Classifier: Programming Language :: Python :: 3.11
Classifier: Programming Language :: Python :: 3.12
Classifier: Programming Language :: Python :: 3 :: Only
Classifier: Topic :: Software Development :: Libraries :: Python Modules
Classifier: Topic :: Software Development :: Version Control :: Git
Classifier: Topic :: System :: Archiving
Classifier: Topic :: Utilities
Classifier: Topic :: Internet :: WWW/HTTP :: Dynamic Content
Classifier: Framework :: AsyncIO
Classifier: Natural Language :: English
Classifier: Natural Language :: Korean
Requires-Python: >=3.8
License-File: LICENSE
Requires-Dist: requests>=2.28.0
Requires-Dist: urllib3<3.0.0,>=1.26.0
Requires-Dist: httpx>=0.24.0
Requires-Dist: aiofiles>=0.8.0
Requires-Dist: asyncio-throttle>=1.0.2
Requires-Dist: certifi>=2022.5.18.1
Requires-Dist: charset-normalizer>=2.0.0
Requires-Dist: idna>=2.8
Requires-Dist: rich>=13.0.0
Provides-Extra: dev
Requires-Dist: pytest>=7.0.0; extra == "dev"
Requires-Dist: pytest-asyncio>=0.21.0; extra == "dev"
Requires-Dist: pytest-cov>=4.0.0; extra == "dev"
Requires-Dist: pytest-mock>=3.10.0; extra == "dev"
Requires-Dist: black>=23.0.0; extra == "dev"
Requires-Dist: isort>=5.12.0; extra == "dev"
Requires-Dist: flake8>=6.0.0; extra == "dev"
Requires-Dist: mypy>=1.0.0; extra == "dev"
Requires-Dist: pre-commit>=3.0.0; extra == "dev"
Provides-Extra: test
Requires-Dist: pytest>=7.0.0; extra == "test"
Requires-Dist: pytest-asyncio>=0.21.0; extra == "test"
Requires-Dist: pytest-cov>=4.0.0; extra == "test"
Requires-Dist: pytest-mock>=3.10.0; extra == "test"
Requires-Dist: coverage[toml]>=7.0.0; extra == "test"
Provides-Extra: docs
Requires-Dist: sphinx>=6.0.0; extra == "docs"
Requires-Dist: sphinx-rtd-theme>=1.2.0; extra == "docs"
Requires-Dist: sphinx-autodoc-typehints>=1.22.0; extra == "docs"
Requires-Dist: myst-parser>=1.0.0; extra == "docs"
Provides-Extra: performance
Requires-Dist: orjson>=3.8.0; extra == "performance"
Requires-Dist: lz4>=4.0.0; extra == "performance"
Requires-Dist: uvloop>=0.17.0; sys_platform != "win32" and extra == "performance"
Provides-Extra: all
Requires-Dist: httpx>=0.24.0; extra == "all"
Requires-Dist: aiofiles>=0.8.0; extra == "all"
Requires-Dist: asyncio-throttle>=1.0.2; extra == "all"
Requires-Dist: orjson>=3.8.0; extra == "all"
Requires-Dist: lz4>=4.0.0; extra == "all"
Requires-Dist: uvloop>=0.17.0; sys_platform != "win32" and extra == "all"
Provides-Extra: full
Requires-Dist: httpx>=0.24.0; extra == "full"
Requires-Dist: aiofiles>=0.8.0; extra == "full"
Requires-Dist: asyncio-throttle>=1.0.2; extra == "full"
Requires-Dist: pytest>=7.0.0; extra == "full"
Requires-Dist: pytest-asyncio>=0.21.0; extra == "full"
Requires-Dist: pytest-cov>=4.0.0; extra == "full"
Requires-Dist: pytest-mock>=3.10.0; extra == "full"
Requires-Dist: black>=23.0.0; extra == "full"
Requires-Dist: isort>=5.12.0; extra == "full"
Requires-Dist: flake8>=6.0.0; extra == "full"
Requires-Dist: mypy>=1.0.0; extra == "full"
Requires-Dist: pre-commit>=3.0.0; extra == "full"
Requires-Dist: coverage[toml]>=7.0.0; extra == "full"
Requires-Dist: sphinx>=6.0.0; extra == "full"
Requires-Dist: sphinx-rtd-theme>=1.2.0; extra == "full"
Requires-Dist: orjson>=3.8.0; extra == "full"
Requires-Dist: lz4>=4.0.0; extra == "full"
Dynamic: license-file
